qosst_sim/__init__.py
qosst_sim/channel.py
qosst_sim/detector.py
qosst_sim/example.py
qosst_sim/modulation/__init__.py
qosst_sim/modulation/binomial_qam.py
qosst_sim/modulation/gaussian_qam.py
qosst_sim/modulation/modulation.py
qosst_sim/modulation/qam.py
qosst_sim/py.typed
qosst_sim/simulator/__init__.py
qosst_sim/simulator/finite_size_simulator.py
qosst_sim/simulator/gaussian_channel_asymptotic_calculator.py
qosst_sim/simulator/gaussian_modulation_asymptotic_calculator.py
qosst_sim/simulator/simulator.py
qosst_sim/utils.py
qosst_sim-0.10.0.dist-info/LICENSE
qosst_sim-0.10.0.dist-info/METADATA
qosst_sim-0.10.0.dist-info/WHEEL
qosst_sim-0.10.0.dist-info/RECORD
