Metadata-Version: 2.1
Name: qosst-sim
Version: 0.10.0
Summary: Simulation module of QOSST.
Home-page: https://github.com/qosst
License: GPLv3
Author: Mayeul Chavanne
Author-email: mayeul.chavanne@ensta-paris.fr
Requires-Python: >=3.9,<3.13
Classifier: Development Status :: 4 - Beta
Classifier: Intended Audience :: Science/Research
Classifier: License :: OSI Approved :: GNU General Public License v3 (GPLv3)
Classifier: License :: Other/Proprietary License
Classifier: Natural Language :: English
Classifier: Operating System :: OS Independent
Classifier: Programming Language :: Python :: 3
Classifier: Programming Language :: Python :: 3.9
Classifier: Programming Language :: Python :: 3.10
Classifier: Programming Language :: Python :: 3.11
Classifier: Programming Language :: Python :: 3.12
Classifier: Topic :: Scientific/Engineering :: Physics
Classifier: Topic :: Security :: Cryptography
Requires-Dist: qosst-core (>=0.10.0,<0.11.0)
Requires-Dist: qosst-skr (>=0.10.0,<0.11.0)
Project-URL: Documentation, https://qosst-sim.readthedocs.io/
Project-URL: Repository, https://github.com/qosst/qosst-sim
